splitfolders/__init__.py
splitfolders/cli.py
splitfolders/split.py
splitfolders/utils.py
split_folders-0.5.0.dist-info/entry_points.txt
split_folders-0.5.0.dist-info/LICENSE
split_folders-0.5.0.dist-info/WHEEL
split_folders-0.5.0.dist-info/METADATA
split_folders-0.5.0.dist-info/RECORD
