Metadata-Version: 2.1
Name: split-folders
Version: 0.5.0
Summary: Split folders with files (e.g. images) into training, validation and test (dataset) folders.
Home-page: https://github.com/jfilter/split-folders
License: MIT
Keywords: machine-learning,training-validation-test,datasets,folders
Author: Johannes Filter
Author-email: hi@jfilter.de
Requires-Python: >=3.6
Classifier: License :: OSI Approved :: MIT License
Classifier: Programming Language :: Python :: 3
Classifier: Programming Language :: Python :: 3.10
Classifier: Programming Language :: Python :: 3.6
Classifier: Programming Language :: Python :: 3.7
Classifier: Programming Language :: Python :: 3.8
Classifier: Programming Language :: Python :: 3.9
Classifier: Topic :: Utilities
Provides-Extra: full
Requires-Dist: tqdm; extra == "full"
Project-URL: Repository, https://github.com/jfilter/split-folders
